{
  "species": "kangaskhan",
  "base_stats": {
    "base_hp": 105,
    "base_attack": 95,
    "base_defense": 80,
    "base_speed": 90,
    "base_sp_attack": 40,
    "base_sp_defense": 80,
    "type_1": "normal",
    "type_2": "normal",
    "catch_rate": 45,
    "exp_yield": 175,
    "ev_yield_hp": 2,
    "ev_yield_attack": 0,
    "ev_yield_defense": 0,
    "ev_yield_speed": 0,
    "ev_yield_sp_attack": 0,
    "ev_yield_sp_defense": 0,
    "item_1": "none",
    "item_2": "none",
    "gender_ratio": -3,
    "egg_cycles": 20,
    "friendship": 70,
    "growth_rate": "medium_fast",
    "egg_group_1": "monster",
    "egg_group_2": "monster",
    "abilities": [
      "early_bird",
      "none"
    ],
    "safari_zone_flee_rate": 125,
    "body_color": "brown",
    "no_flip": false
  },
  "egg_moves": [
    "stomp",
    "foresight",
    "focus_energy",
    "safeguard",
    "disable",
    "counter",
    "crush_claw",
    "substitute"
  ],
  "evolutions": [],
  "level_up_moves": [
    {
      "level": 1,
      "move": "comet_punch"
    },
    {
      "level": 1,
      "move": "leer"
    },
    {
      "level": 7,
      "move": "bite"
    },
    {
      "level": 13,
      "move": "tail_whip"
    },
    {
      "level": 19,
      "move": "fake_out"
    },
    {
      "level": 25,
      "move": "mega_punch"
    },
    {
      "level": 31,
      "move": "rage"
    },
    {
      "level": 37,
      "move": "endure"
    },
    {
      "level": 43,
      "move": "dizzy_punch"
    },
    {
      "level": 49,
      "move": "reversal"
    }
  ],
  "tm_hm_moves": [
    "tm01_focus_punch",
    "tm03_water_pulse",
    "tm05_roar",
    "tm06_toxic",
    "tm07_hail",
    "tm10_hidden_power",
    "tm11_sunny_day",
    "tm13_ice_beam",
    "tm14_blizzard",
    "tm15_hyper_beam",
    "tm17_protect",
    "tm18_rain_dance",
    "tm21_frustration",
    "tm22_solarbeam",
    "tm23_iron_tail",
    "tm24_thunderbolt",
    "tm25_thunder",
    "tm26_earthquake",
    "tm27_return",
    "tm28_dig",
    "tm30_shadow_ball",
    "tm31_brick_break",
    "tm32_double_team",
    "tm34_shock_wave",
    "tm35_flamethrower",
    "tm37_sandstorm",
    "tm38_fire_blast",
    "tm39_rock_tomb",
    "tm40_aerial_ace",
    "tm42_facade",
    "tm43_secret_power",
    "tm44_rest",
    "tm45_attract",
    "tm46_thief",
    "hm01_cut",
    "hm03_surf",
    "hm04_strength",
    "hm06_rock_smash"
  ],
  "tutor_moves": [
    "mega_punch",
    "mega_kick",
    "body_slam",
    "double_edge",
    "counter",
    "seismic_toss",
    "mimic",
    "rock_slide",
    "substitute"
  ]
}
