{
  "id": "MAP_VERMILION_CITY_HOUSE3",
  "name": "VermilionCity_House3",
  "layout": "LAYOUT_HOUSE1",
  "music": "MUS_KUCHIBA",
  "region_map_section": "MAPSEC_VERMILION_CITY",
  "requires_flash": false,
  "weather": "WEATHER_NONE",
  "map_type": "MAP_TYPE_INDOOR",
  "allow_cycling": false,
  "allow_escaping": false,
  "allow_running": false,
  "show_map_name": false,
  "floor_number": 0,
  "battle_scene": "MAP_BATTLE_SCENE_NORMAL",
  "connections": null,
  "object_events": [],
  "warp_events": [
    {
      "x": 3,
      "y": 7,
      "elevation": 3,
      "dest_map": "MAP_VERMILION_CITY",
      "dest_warp_id": 8
    },
    {
      "x": 4,
      "y": 7,
      "elevation": 3,
      "dest_map": "MAP_VERMILION_CITY",
      "dest_warp_id": 8
    },
    {
      "x": 5,
      "y": 7,
      "elevation": 3,
      "dest_map": "MAP_VERMILION_CITY",
      "dest_warp_id": 8
    }
  ],
  "coord_events": [],
  "bg_events": [
    {
      "type": "sign",
      "x": 6,
      "y": 4,
      "elevation": 3,
      "player_facing_dir": "BG_EVENT_PLAYER_FACING_ANY",
      "script": "VermilionCity_House3_EventScript_Letter"
    }
  ]
}