{
  "id": "MAP_SILPH_CO_6F",
  "name": "SilphCo_6F",
  "layout": "LAYOUT_SILPH_CO_6F",
  "music": "MUS_SHIRUHU",
  "region_map_section": "MAPSEC_SILPH_CO",
  "requires_flash": false,
  "weather": "WEATHER_NONE",
  "map_type": "MAP_TYPE_8",
  "unknown_18": 0,
  "unknown_19": 7,
  "elevator_flag": 6,
  "battle_scene": "BATTLE_SCENE_0",
  "connections": null,
  "object_events": [
    {
      "graphics_id": "49",
      "x": 21,
      "y": 5,
      "elevation": 3,
      "movement_type": "10",
      "movement_range_x": 1,
      "movement_range_y": 1,
      "trainer_type": 1,
      "trainer_sight_or_berry_tree_id": 2,
      "script": "SilphCo_6F_EventScript_161956",
      "flag": "83"
    },
    {
      "graphics_id": "47",
      "x": 23,
      "y": 9,
      "elevation": 3,
      "movement_type": "8",
      "movement_range_x": 1,
      "movement_range_y": 1,
      "trainer_type": 0,
      "trainer_sight_or_berry_tree_id": 0,
      "script": "SilphCo_6F_EventScript_1618D3",
      "flag": "0"
    },
    {
      "graphics_id": "48",
      "x": 24,
      "y": 9,
      "elevation": 3,
      "movement_type": "8",
      "movement_range_x": 1,
      "movement_range_y": 1,
      "trainer_type": 0,
      "trainer_sight_or_berry_tree_id": 0,
      "script": "SilphCo_6F_EventScript_1618F4",
      "flag": "0"
    },
    {
      "graphics_id": "47",
      "x": 22,
      "y": 13,
      "elevation": 3,
      "movement_type": "7",
      "movement_range_x": 1,
      "movement_range_y": 1,
      "trainer_type": 0,
      "trainer_sight_or_berry_tree_id": 0,
      "script": "SilphCo_6F_EventScript_161891",
      "flag": "0"
    },
    {
      "graphics_id": "47",
      "x": 14,
      "y": 9,
      "elevation": 3,
      "movement_type": "1",
      "movement_range_x": 1,
      "movement_range_y": 1,
      "trainer_type": 0,
      "trainer_sight_or_berry_tree_id": 0,
      "script": "SilphCo_6F_EventScript_1618B2",
      "flag": "0"
    },
    {
      "graphics_id": "48",
      "x": 16,
      "y": 12,
      "elevation": 3,
      "movement_type": "10",
      "movement_range_x": 1,
      "movement_range_y": 1,
      "trainer_type": 0,
      "trainer_sight_or_berry_tree_id": 0,
      "script": "SilphCo_6F_EventScript_161915",
      "flag": "0"
    },
    {
      "graphics_id": "55",
      "x": 9,
      "y": 11,
      "elevation": 3,
      "movement_type": "8",
      "movement_range_x": 1,
      "movement_range_y": 1,
      "trainer_type": 1,
      "trainer_sight_or_berry_tree_id": 4,
      "script": "SilphCo_6F_EventScript_16193F",
      "flag": "83"
    },
    {
      "graphics_id": "92",
      "x": 2,
      "y": 14,
      "elevation": 3,
      "movement_type": "8",
      "movement_range_x": 1,
      "movement_range_y": 1,
      "trainer_type": 0,
      "trainer_sight_or_berry_tree_id": 0,
      "script": "SilphCo_6F_EventScript_1BE8C1",
      "flag": "403"
    },
    {
      "graphics_id": "92",
      "x": 1,
      "y": 17,
      "elevation": 3,
      "movement_type": "8",
      "movement_range_x": 1,
      "movement_range_y": 1,
      "trainer_type": 0,
      "trainer_sight_or_berry_tree_id": 0,
      "script": "SilphCo_6F_EventScript_1BE8CE",
      "flag": "404"
    },
    {
      "graphics_id": "49",
      "x": 18,
      "y": 17,
      "elevation": 3,
      "movement_type": "9",
      "movement_range_x": 1,
      "movement_range_y": 1,
      "trainer_type": 1,
      "trainer_sight_or_berry_tree_id": 2,
      "script": "SilphCo_6F_EventScript_16196D",
      "flag": "83"
    }
  ],
  "warp_events": [
    {
      "x": 14,
      "y": 2,
      "elevation": 3,
      "dest_map": "MAP_SILPH_CO_7F",
      "dest_warp_id": 0
    },
    {
      "x": 29,
      "y": 5,
      "elevation": 3,
      "dest_map": "MAP_SILPH_CO_2F",
      "dest_warp_id": 4
    },
    {
      "x": 26,
      "y": 2,
      "elevation": 3,
      "dest_map": "MAP_SILPH_CO_5F",
      "dest_warp_id": 2
    },
    {
      "x": 2,
      "y": 6,
      "elevation": 3,
      "dest_map": "MAP_SILPH_CO_4F",
      "dest_warp_id": 1
    },
    {
      "x": 20,
      "y": 3,
      "elevation": 0,
      "dest_map": "MAP_SILPH_CO_ELEVATOR",
      "dest_warp_id": 0
    }
  ],
  "coord_events": [],
  "bg_events": [
    {
      "type": "bg_event_type_0",
      "x": 6,
      "y": 15,
      "elevation": 0,
      "script": "SilphCo_6F_EventScript_1A8A05"
    },
    {
      "type": "bg_event_type_0",
      "x": 6,
      "y": 16,
      "elevation": 0,
      "script": "SilphCo_6F_EventScript_1A8A05"
    },
    {
      "type": "bg_event_type_0",
      "x": 5,
      "y": 15,
      "elevation": 0,
      "script": "SilphCo_6F_EventScript_1A8A05"
    },
    {
      "type": "bg_event_type_0",
      "x": 5,
      "y": 16,
      "elevation": 0,
      "script": "SilphCo_6F_EventScript_1A8A05"
    },
    {
      "type": "hidden_item",
      "x": 1,
      "y": 8,
      "elevation": 0,
      "item": "ITEM_CARBOS",
      "flag": "HIDDEN_ITEM_SILPH_CO_6F_CARBOS",
      "unknown": 1
    },
    {
      "type": "bg_event_type_0",
      "x": 25,
      "y": 1,
      "elevation": 0,
      "script": "SilphCo_6F_EventScript_161936"
    }
  ]
}