{
  "id": "MAP_TWO_ISLAND_POKEMON_CENTER_1F",
  "name": "TwoIsland_PokemonCenter_1F",
  "layout": "LAYOUT_POKEMON_CENTER_1F",
  "music": "BGM_FRLG_POKEMON_CENTER",
  "region_map_section": "MAPSEC_TWO_ISLAND",
  "requires_flash": false,
  "weather": "WEATHER_NONE",
  "map_type": "MAP_TYPE_8",
  "unknown_18": 0,
  "unknown_19": 0,
  "elevator_flag": 0,
  "battle_scene": "BATTLE_SCENE_0",
  "connections": null,
  "object_events": [
    {
      "graphics_id": "64",
      "x": 7,
      "y": 2,
      "elevation": 3,
      "movement_type": "8",
      "movement_range_x": 1,
      "movement_range_y": 1,
      "trainer_type": 0,
      "trainer_sight_or_berry_tree_id": 0,
      "script": "TwoIsland_PokemonCenter_1F_EventScript_1717C3",
      "flag": "0"
    },
    {
      "graphics_id": "51",
      "x": 11,
      "y": 5,
      "elevation": 3,
      "movement_type": "8",
      "movement_range_x": 1,
      "movement_range_y": 1,
      "trainer_type": 0,
      "trainer_sight_or_berry_tree_id": 0,
      "script": "TwoIsland_PokemonCenter_1F_EventScript_1717CC",
      "flag": "0"
    },
    {
      "graphics_id": "20",
      "x": 4,
      "y": 4,
      "elevation": 3,
      "movement_type": "5",
      "movement_range_x": 1,
      "movement_range_y": 1,
      "trainer_type": 0,
      "trainer_sight_or_berry_tree_id": 0,
      "script": "TwoIsland_PokemonCenter_1F_EventScript_1717D5",
      "flag": "0"
    }
  ],
  "warp_events": [
    {
      "x": 7,
      "y": 8,
      "elevation": 3,
      "dest_map": "MAP_TWO_ISLAND",
      "dest_warp_id": 2
    },
    {
      "x": 1,
      "y": 6,
      "elevation": 4,
      "dest_map": "MAP_TWO_ISLAND_POKEMON_CENTER_2F",
      "dest_warp_id": 0
    }
  ],
  "coord_events": [],
  "bg_events": []
}
