{
  "id": "MAP_ROUTE3",
  "name": "Route3",
  "layout": "LAYOUT_ROUTE3",
  "music": "MUS_LOAD02",
  "region_map_section": "MAPSEC_ROUTE_3",
  "requires_flash": false,
  "weather": "WEATHER_SUNNY",
  "map_type": "MAP_TYPE_ROUTE",
  "allow_cycling": true,
  "allow_escaping": false,
  "allow_running": true,
  "show_map_name": true,
  "floor_number": 0,
  "battle_scene": "MAP_BATTLE_SCENE_NORMAL",
  "connections": [
    {
      "map": "MAP_ROUTE4",
      "offset": 60,
      "direction": "up"
    },
    {
      "map": "MAP_PEWTER_CITY",
      "offset": -10,
      "direction": "left"
    }
  ],
  "object_events": [],
  "warp_events": [],
  "coord_events": [],
  "bg_events": [
    {
      "type": "sign",
      "x": 72,
      "y": 11,
      "elevation": 0,
      "player_facing_dir": "BG_EVENT_PLAYER_FACING_ANY",
      "script": "Route3_EventScript_RouteSign"
    }
  ]
}