{
  "id": "MAP_BIRTH_ISLAND_EXTERIOR",
  "name": "BirthIsland_Exterior",
  "layout": "LAYOUT_BIRTH_ISLAND_EXTERIOR",
  "music": "0xFFFF",
  "region_map_section": "MAPSEC_BIRTH_ISLAND",
  "requires_flash": false,
  "weather": "WEATHER_NONE",
  "map_type": "MAP_TYPE_ROUTE",
  "allow_cycling": false,
  "allow_escaping": false,
  "allow_running": true,
  "show_map_name": true,
  "floor_number": 0,
  "battle_scene": "MAP_BATTLE_SCENE_NORMAL",
  "connections": null,
  "object_events": [],
  "warp_events": [
    {
      "x": 15,
      "y": 24,
      "elevation": 3,
      "dest_map": "MAP_BIRTH_ISLAND_HARBOR",
      "dest_warp_id": 0
    }
  ],
  "coord_events": [],
  "bg_events": []
}