{
  "id": "MAP_CELADON_CITY_DEPARTMENT_STORE_1F",
  "name": "CeladonCity_DepartmentStore_1F",
  "layout": "LAYOUT_CELADON_CITY_DEPARTMENT_STORE_1F",
  "music": "BGM_FRLG_POKEMON_CENTER",
  "region_map_section": "MAPSEC_CELADON_CITY",
  "requires_flash": false,
  "weather": "WEATHER_NONE",
  "map_type": "MAP_TYPE_8",
  "unknown_18": 0,
  "unknown_19": 4,
  "elevator_flag": 1,
  "battle_scene": "BATTLE_SCENE_0",
  "connections": null,
  "object_events": [
    {
      "graphics_id": "48",
      "x": 6,
      "y": 10,
      "elevation": 3,
      "movement_type": "8",
      "movement_range_x": 1,
      "movement_range_y": 1,
      "trainer_type": 0,
      "trainer_sight_or_berry_tree_id": 0,
      "script": "CeladonCity_DepartmentStore_1F_EventScript_16BAD9",
      "flag": "0"
    }
  ],
  "warp_events": [
    {
      "x": 1,
      "y": 15,
      "elevation": 0,
      "dest_map": "MAP_CELADON_CITY",
      "dest_warp_id": 1
    },
    {
      "x": 2,
      "y": 14,
      "elevation": 3,
      "dest_map": "MAP_CELADON_CITY",
      "dest_warp_id": 1
    },
    {
      "x": 3,
      "y": 15,
      "elevation": 0,
      "dest_map": "MAP_CELADON_CITY",
      "dest_warp_id": 1
    },
    {
      "x": 9,
      "y": 15,
      "elevation": 0,
      "dest_map": "MAP_CELADON_CITY",
      "dest_warp_id": 2
    },
    {
      "x": 10,
      "y": 14,
      "elevation": 3,
      "dest_map": "MAP_CELADON_CITY",
      "dest_warp_id": 2
    },
    {
      "x": 11,
      "y": 15,
      "elevation": 0,
      "dest_map": "MAP_CELADON_CITY",
      "dest_warp_id": 2
    },
    {
      "x": 6,
      "y": 1,
      "elevation": 0,
      "dest_map": "MAP_CELADON_CITY_DEPARTMENT_STORE_ELEVATOR",
      "dest_warp_id": 0
    },
    {
      "x": 4,
      "y": 2,
      "elevation": 3,
      "dest_map": "MAP_CELADON_CITY_DEPARTMENT_STORE_2F",
      "dest_warp_id": 1
    }
  ],
  "coord_events": [],
  "bg_events": [
    {
      "type": "bg_event_type_0",
      "x": 9,
      "y": 11,
      "elevation": 0,
      "script": "CeladonCity_DepartmentStore_1F_EventScript_16BAE2"
    },
    {
      "type": "bg_event_type_0",
      "x": 8,
      "y": 1,
      "elevation": 0,
      "script": "CeladonCity_DepartmentStore_1F_EventScript_16BAEB"
    }
  ]
}
